git_short-1.0.1.dist-info/licenses/LICENSE
tools/__init__.py
tools/cli.py
tools/commands.py
git_short-1.0.1.dist-info/METADATA
git_short-1.0.1.dist-info/WHEEL
git_short-1.0.1.dist-info/entry_points.txt
git_short-1.0.1.dist-info/top_level.txt
git_short-1.0.1.dist-info/RECORD
